px4sitl/__init__.py
px4sitl/cli.py
px4sitl-0.0.2.data/data/share/applications/org.osrfoundation.mcmillan_sitl.desktop
px4sitl-0.0.2.data/data/share/applications/org.osrfoundation.yosemite_sitl.desktop
px4sitl-0.0.2.dist-info/DESCRIPTION.rst
px4sitl-0.0.2.dist-info/METADATA
px4sitl-0.0.2.dist-info/RECORD
px4sitl-0.0.2.dist-info/WHEEL
px4sitl-0.0.2.dist-info/entry_points.txt
px4sitl-0.0.2.dist-info/metadata.json
px4sitl-0.0.2.dist-info/top_level.txt
